html_dgraph_poster/__init__.py
html_dgraph_poster/converter.py
html_dgraph_poster/create_account.py
html_dgraph_poster/errors.py
html_dgraph_poster/html_to_telegraph.py
html_dgraph_poster/upload_images.py
html_dgraph_poster/utils.py
html_dgraph_poster-0.5.0.dist-info/LICENSE
html_dgraph_poster-0.5.0.dist-info/METADATA
html_dgraph_poster-0.5.0.dist-info/WHEEL
html_dgraph_poster-0.5.0.dist-info/top_level.txt
html_dgraph_poster-0.5.0.dist-info/RECORD
