Metadata-Version: 2.1
Name: html-dgraph-poster
Version: 0.5.0
Summary: Posts your html to telegra.ph blogging service
Home-page: https://github.com/mercuree/html-telegraph-poster
Author: Garry G
Author-email: mercuree.lab@gmail.com
License: MIT
Keywords: telegra.ph post html telegram
Classifier: Operating System :: OS Independent
Classifier: Programming Language :: Python :: 3
Classifier: License :: OSI Approved :: MIT License
License-File: LICENSE
Requires-Dist: lxml
Requires-Dist: requests
Requires-Dist: requests-toolbelt
